zk_doc_mcp/__init__.py
zk_doc_mcp/__main__.py
zk_doc_mcp/doc_indexer.py
zk_doc_mcp/feedback_manager.py
zk_doc_mcp/git_manager.py
zk_doc_mcp/logger.py
zk_doc_mcp/server.py
zk_doc_mcp_server-0.8.1.dist-info/METADATA
zk_doc_mcp_server-0.8.1.dist-info/WHEEL
zk_doc_mcp_server-0.8.1.dist-info/entry_points.txt
zk_doc_mcp_server-0.8.1.dist-info/licenses/LICENSE
zk_doc_mcp_server-0.8.1.dist-info/RECORD
