Metadata-Version: 2.4
Name: zk-doc-mcp-server
Version: 0.8.1
Summary: MCP server for searching ZK Framework documentation
Project-URL: Homepage, https://github.com/zkoss/zk-doc-mcp
Project-URL: Documentation, https://github.com/zkoss/zk-doc-mcp#readme
Project-URL: Repository, https://github.com/zkoss/zk-doc-mcp
Project-URL: Issues, https://github.com/zkoss/zk-doc-mcp/issues
Author: ZK Doc MCP Contributors
License: MIT License
License-File: LICENSE
Keywords: ai,documentation,mcp,search,zk
Classifier: Development Status :: 3 - Alpha
Classifier: Intended Audience :: Developers
Classifier: License :: OSI Approved :: MIT License
Classifier: Programming Language :: Python :: 3
Classifier: Programming Language :: Python :: 3.10
Classifier: Programming Language :: Python :: 3.11
Classifier: Programming Language :: Python :: 3.12
Requires-Python: >=3.10
Requires-Dist: fastmcp>=0.1.0
Requires-Dist: httpx>=0.28.1
Requires-Dist: mcp[cli]>=1.21.0
Provides-Extra: dev
Requires-Dist: black>=23.0.0; extra == 'dev'
Requires-Dist: mypy>=1.0.0; extra == 'dev'
Requires-Dist: pytest-cov>=4.0.0; extra == 'dev'
Requires-Dist: pytest>=7.0.0; extra == 'dev'
Requires-Dist: ruff>=0.1.0; extra == 'dev'
Provides-Extra: search
Requires-Dist: chromadb>=0.6.0; extra == 'search'
